aadinspector/__init__.py
aadinspector/b2c_jwt_inspector.py
aadinspector-1.1.6.dist-info/LICENSE
aadinspector-1.1.6.dist-info/METADATA
aadinspector-1.1.6.dist-info/WHEEL
aadinspector-1.1.6.dist-info/top_level.txt
aadinspector-1.1.6.dist-info/RECORD
