Metadata-Version: 2.1
Name: aadinspector
Version: 1.1.6
Summary: This package help to validate azure ad jwt token.
Author-email: Dinesh Kushwaha <2kush.dinesh@gmail.com>
License: MIT License        
Project-URL: Homepage, https://github.com/dinesh-kushwaha/aadinspector
Project-URL: Bug Tracker, https://github.com/dinesh-kushwaha/aadinspector/issues
Keywords: python,azure active directory,jwt,token,validation
Classifier: Programming Language :: Python :: 3
Classifier: License :: OSI Approved :: MIT License
Classifier: Operating System :: OS Independent
Requires-Python: >=3.6
License-File: LICENSE
Requires-Dist: cryptography (==37.0.4)
Requires-Dist: PyJWT (==2.4.0)
Requires-Dist: requests (==2.28.1)
